ebbs/__init__.py
ebbs/__main__.py
ebbs/ebbs.py
ebbs/build/__init__.py
ebbs/build/build_default.py
ebbs-2.2.32.dist-info/METADATA
ebbs-2.2.32.dist-info/WHEEL
ebbs-2.2.32.dist-info/entry_points.txt
ebbs-2.2.32.dist-info/top_level.txt
ebbs-2.2.32.dist-info/RECORD
