Metadata-Version: 2.1
Name: ebbs
Version: 2.2.32
Summary: eons Basic Build System
Home-page: https://github.com/eons-dev/ebbs.exe
Author: eons
Author-email: support@eons.llc
Project-URL: Bug Tracker, https://github.com/eons-dev/ebbs.exe/issues
Classifier: Programming Language :: Python :: 3
Classifier: License :: OSI Approved :: MIT License
Classifier: Operating System :: OS Independent
Classifier: Development Status :: 4 - Beta
Requires-Python: >=3.7
Requires-Dist: eons
Requires-Dist: jsonpickle
